gitswitch/__init__.py
gitswitch/__main__.py
gitswitch/helpers.py
gitswitch/installer.py
gitswitch/switcher.py
pyGitSwitch-0.4.0.dist-info/LICENSE
pyGitSwitch-0.4.0.dist-info/METADATA
pyGitSwitch-0.4.0.dist-info/WHEEL
pyGitSwitch-0.4.0.dist-info/entry_points.txt
pyGitSwitch-0.4.0.dist-info/top_level.txt
pyGitSwitch-0.4.0.dist-info/RECORD
