Metadata-Version: 2.1
Name: pyGitSwitch
Version: 0.4.0
Summary: Github Desktop Multi account switcher
Home-page: https://github.com/AnvithLobo/gitswitch
Author: Anvith Lobo
Author-email: anvithlobo@gmail.com
License: MIT
Project-URL: Source Code, https://github.com/AnvithLobo/pygitswitch
Project-URL: Bug Tracker, https://github.com/AnvithLobo/pygitswitch/issues
Project-URL: Documentation, https://github.com/AnvithLobo/pygitswitch/wiki
Platform: UNKNOWN
Classifier: Development Status :: 4 - Beta
Classifier: Environment :: Console
Classifier: Intended Audience :: Developers
Classifier: Intended Audience :: System Administrators
Classifier: License :: OSI Approved :: MIT License
Classifier: Natural Language :: English
Classifier: Operating System :: Microsoft :: Windows
Classifier: Programming Language :: Python :: 3
Classifier: Programming Language :: Python :: 3 :: Only
Classifier: Programming Language :: Python :: 3.6
Classifier: Programming Language :: Python :: 3.7
Classifier: Programming Language :: Python :: 3.8
Classifier: Programming Language :: Python :: 3.9
Classifier: Programming Language :: Python :: 3.10
Classifier: Topic :: Software Development :: Version Control :: Git
Classifier: Topic :: System :: Systems Administration
Classifier: Topic :: Utilities
Requires-Python: >=3.6
License-File: LICENSE
